<PAMDataset>
  <PAMRasterBand band="1">
    <Metadata>
      <MDI key="STATISTICS_COVARIANCES">0.0128037951058432</MDI>
      <MDI key="STATISTICS_EXCLUDEDVALUES"></MDI>
      <MDI key="STATISTICS_MAXIMUM">0.55504316091537</MDI>
      <MDI key="STATISTICS_MEAN">0.15525645488708</MDI>
      <MDI key="STATISTICS_MINIMUM">0.00033564993645996</MDI>
      <MDI key="STATISTICS_SKIPFACTORX">1</MDI>
      <MDI key="STATISTICS_SKIPFACTORY">1</MDI>
      <MDI key="STATISTICS_STDDEV">0.11315385590356</MDI>
    </Metadata>
  </PAMRasterBand>
</PAMDataset>
