<PAMDataset>
  <PAMRasterBand band="1">
    <Metadata>
      <MDI key="STATISTICS_COVARIANCES">0.03591196162022286</MDI>
      <MDI key="STATISTICS_EXCLUDEDVALUES"></MDI>
      <MDI key="STATISTICS_MAXIMUM">0.93852317333221</MDI>
      <MDI key="STATISTICS_MEAN">0.34062651055986</MDI>
      <MDI key="STATISTICS_MINIMUM">5.637629510602e-05</MDI>
      <MDI key="STATISTICS_SKIPFACTORX">1</MDI>
      <MDI key="STATISTICS_SKIPFACTORY">1</MDI>
      <MDI key="STATISTICS_STDDEV">0.18950451609453</MDI>
    </Metadata>
  </PAMRasterBand>
</PAMDataset>
